<?xml version="1.0" encoding="UTF-8"?>
<magicdraw><package humanType="Package" icon="UX_files/icon_21279106.png" id="_16_8_2030113_1324117401703_423319_14192"><member humanName="Member"><package humanType="Package" icon="UX_files/icon_21279106.png" name="Professor" refid="_16_8_2030113_1324131014140_915852_16637"/><association humanType="Association" icon="UX_files/icon_10257241.png" isRelationship="true" name="selectProject()" refid="_16_5_4_2030113_1323887081125_272804_1617"/><package humanType="Package" icon="UX_files/icon_21279106.png" name="Stereotypes" refid="_16_6_27c0135_1323936072525_914579_12662"/><package humanType="Package" icon="UX_files/icon_21279106.png" name="Student" refid="_16_8_2030113_1324131980640_668457_18100"/><association humanType="Association" icon="UX_files/icon_10257241.png" isRelationship="true" name="upload error" refid="_16_5_4_2030113_1323986344687_601126_1751"/></member><name humanName="Name" mode="standard,expert">Resources</name><namespace humanName="Namespace" humanType="Model" icon="UX_files/icon_894824.png" name="Data" refid="eee_1045467100313_135436_1"/><nestedPackage humanName="Nested Package"><package humanType="Package" icon="UX_files/icon_21279106.png" name="Professor" refid="_16_8_2030113_1324131014140_915852_16637"/><package humanType="Package" icon="UX_files/icon_21279106.png" name="Stereotypes" refid="_16_6_27c0135_1323936072525_914579_12662"/><package humanType="Package" icon="UX_files/icon_21279106.png" name="Student" refid="_16_8_2030113_1324131980640_668457_18100"/></nestedPackage><nestingPackage humanName="Nesting Package" humanType="Model" icon="UX_files/icon_894824.png" name="Data" refid="eee_1045467100313_135436_1"/><ownedElement humanName="Owned Element"><package humanType="Package" icon="UX_files/icon_21279106.png" name="Professor" refid="_16_8_2030113_1324131014140_915852_16637"/><association humanType="Association" icon="UX_files/icon_10257241.png" isRelationship="true" name="selectProject()" refid="_16_5_4_2030113_1323887081125_272804_1617"/><package humanType="Package" icon="UX_files/icon_21279106.png" name="Stereotypes" refid="_16_6_27c0135_1323936072525_914579_12662"/><package humanType="Package" icon="UX_files/icon_21279106.png" name="Student" refid="_16_8_2030113_1324131980640_668457_18100"/><association humanType="Association" icon="UX_files/icon_10257241.png" isRelationship="true" name="upload error" refid="_16_5_4_2030113_1323986344687_601126_1751"/></ownedElement><ownedMember humanName="Owned Member"><package humanType="Package" icon="UX_files/icon_21279106.png" name="Professor" refid="_16_8_2030113_1324131014140_915852_16637"/><association humanType="Association" icon="UX_files/icon_10257241.png" isRelationship="true" name="selectProject()" refid="_16_5_4_2030113_1323887081125_272804_1617"/><package humanType="Package" icon="UX_files/icon_21279106.png" name="Stereotypes" refid="_16_6_27c0135_1323936072525_914579_12662"/><package humanType="Package" icon="UX_files/icon_21279106.png" name="Student" refid="_16_8_2030113_1324131980640_668457_18100"/><association humanType="Association" icon="UX_files/icon_10257241.png" isRelationship="true" name="upload error" refid="_16_5_4_2030113_1323986344687_601126_1751"/></ownedMember><ownedType humanName="Owned Type"><association humanType="Association" icon="UX_files/icon_10257241.png" isRelationship="true" name="selectProject()" refid="_16_5_4_2030113_1323887081125_272804_1617"/><association humanType="Association" icon="UX_files/icon_10257241.png" isRelationship="true" name="upload error" refid="_16_5_4_2030113_1323986344687_601126_1751"/></ownedType><owner humanName="Owner" humanType="Model" icon="UX_files/icon_894824.png" mode="standard,expert" name="Data" refid="eee_1045467100313_135436_1"/><owningPackage humanName="Owning Package" humanType="Model" icon="UX_files/icon_894824.png" name="Data" refid="eee_1045467100313_135436_1"/><packagedElement humanName="Packaged Element"><package humanType="Package" icon="UX_files/icon_21279106.png" name="Professor" refid="_16_8_2030113_1324131014140_915852_16637"/><association humanType="Association" icon="UX_files/icon_10257241.png" isRelationship="true" name="selectProject()" refid="_16_5_4_2030113_1323887081125_272804_1617"/><package humanType="Package" icon="UX_files/icon_21279106.png" name="Stereotypes" refid="_16_6_27c0135_1323936072525_914579_12662"/><package humanType="Package" icon="UX_files/icon_21279106.png" name="Student" refid="_16_8_2030113_1324131980640_668457_18100"/><association humanType="Association" icon="UX_files/icon_10257241.png" isRelationship="true" name="upload error" refid="_16_5_4_2030113_1323986344687_601126_1751"/></packagedElement><qualifiedName humanName="Qualified Name" mode="expert">Resources</qualifiedName><visibility humanName="Visibility">public</visibility></package></magicdraw>