<?xml version="1.0" encoding="UTF-8"?>
<magicdraw><literalstring humanType="Literal String" icon="UX_files/icon_5212354.png" id="_16_8_2030113_1324403927828_758843_14735"><name humanName="Name"/><owner humanName="Owner" humanType="Slot" icon="UX_files/icon_558865.png" mode="expert" refid="_16_8_2030113_1324403927828_886911_14734"/><owningSlot humanName="Owning Slot" humanType="Slot" icon="UX_files/icon_558865.png" refid="_16_8_2030113_1324403927828_886911_14734"/><qualifiedName humanName="Qualified Name">Professor::GUI::Artifacts::Delivered Artifacts::::</qualifiedName><text humanName="Text" mode="standard">12/17/11 4:13 PM</text><value humanName="Value" mode="standard,expert">12/17/11 4:13 PM</value><visibility humanName="Visibility">public</visibility></literalstring></magicdraw>