<?xml version="1.0" encoding="UTF-8"?>
<magicdraw><literalstring humanType="Literal String" icon="UX_files/icon_5212354.png" id="_16_8_2030113_1324403927328_293389_13991"><name humanName="Name"/><owner humanName="Owner" humanType="Slot" icon="UX_files/icon_558865.png" mode="expert" refid="_16_8_2030113_1324403927328_457928_13990"/><owningSlot humanName="Owning Slot" humanType="Slot" icon="UX_files/icon_558865.png" refid="_16_8_2030113_1324403927328_457928_13990"/><qualifiedName humanName="Qualified Name">Resources::Student::::::</qualifiedName><text humanName="Text" mode="standard">Match!</text><value humanName="Value" mode="standard,expert">Match!</value><visibility humanName="Visibility">public</visibility></literalstring></magicdraw>