<?xml version="1.0" encoding="UTF-8"?>
<magicdraw><class humanType="Class" icon="UX_files/icon_3322787.png" id="_16_6_27c0135_1323963669905_411994_12867"><appliedStereotype humanName="Applied Stereotype" mode="expert"><stereotype humanType="Stereotype" icon="UX_files/icon_1202637.png" name="Form" refid="_16_6_27c0135_1323955957352_932767_12784"><property humanName="base_Class" humanType="Property" icon="UX_files/icon_18207639.png" name="base_Class" refid="_16_6_27c0135_1323955957352_875991_12786"/></stereotype></appliedStereotype><appliedStereotypeInstance humanName="Applied Stereotype Instance" humanType="Instance Specification" icon="UX_files/icon_22306013.png" name="" refid="_16_6_27c0135_1323963703188_246104_12885"/><attribute humanName="Attribute"><property humanType="Property" icon="UX_files/icon_18207639.png" name="" refid="_16_6_27c0135_1323963805355_429964_12898"/><property humanType="Property" icon="UX_files/icon_18207639.png" name="" refid="_16_6_27c0135_1323964526145_780649_12996"/><property humanType="Property" icon="UX_files/icon_18207639.png" name="" refid="_16_5_4_2030113_1323967839093_586719_406"/><property humanType="Property" icon="UX_files/icon_18207639.png" name="" refid="_16_5_4_2030113_1323973054390_652871_2236"/><property humanType="Property" icon="UX_files/icon_18207639.png" name="" refid="_16_5_4_2030113_1323986344703_930940_1752"/><property humanType="Property" icon="UX_files/icon_18207639.png" name="" refid="_16_5_4_2030113_1323988334593_68790_2532"/><property humanType="Property" icon="UX_files/icon_18207639.png" name="deliverable" refid="_16_6_27c0135_1323963711132_828711_12886"/></attribute><feature humanName="Feature"><property humanType="Property" icon="UX_files/icon_18207639.png" name="" refid="_16_6_27c0135_1323963805355_429964_12898"/><property humanType="Property" icon="UX_files/icon_18207639.png" name="" refid="_16_6_27c0135_1323964526145_780649_12996"/><property humanType="Property" icon="UX_files/icon_18207639.png" name="" refid="_16_5_4_2030113_1323967839093_586719_406"/><property humanType="Property" icon="UX_files/icon_18207639.png" name="" refid="_16_5_4_2030113_1323973054390_652871_2236"/><property humanType="Property" icon="UX_files/icon_18207639.png" name="" refid="_16_5_4_2030113_1323986344703_930940_1752"/><property humanType="Property" icon="UX_files/icon_18207639.png" name="" refid="_16_5_4_2030113_1323988334593_68790_2532"/><property humanType="Property" icon="UX_files/icon_18207639.png" name="deliverable" refid="_16_6_27c0135_1323963711132_828711_12886"/><operation humanType="Operation" icon="UX_files/icon_25941162.png" name="uploadArtifact" refid="_16_6_27c0135_1323963764639_574514_12888"/></feature><isAbstract humanName="Is Abstract">false</isAbstract><isActive humanName="Is Active">false</isActive><isFinalSpecialization humanName="Is Final Specialization" mode="expert">false</isFinalSpecialization><isLeaf humanName="Is Leaf">false</isLeaf><member humanName="Member"><property humanType="Property" icon="UX_files/icon_18207639.png" name="" refid="_16_6_27c0135_1323963805355_429964_12898"/><property humanType="Property" icon="UX_files/icon_18207639.png" name="" refid="_16_6_27c0135_1323964526145_780649_12996"/><property humanType="Property" icon="UX_files/icon_18207639.png" name="" refid="_16_5_4_2030113_1323967839093_586719_406"/><property humanType="Property" icon="UX_files/icon_18207639.png" name="" refid="_16_5_4_2030113_1323973054390_652871_2236"/><property humanType="Property" icon="UX_files/icon_18207639.png" name="" refid="_16_5_4_2030113_1323986344703_930940_1752"/><property humanType="Property" icon="UX_files/icon_18207639.png" name="" refid="_16_5_4_2030113_1323988334593_68790_2532"/><property humanType="Property" icon="UX_files/icon_18207639.png" name="deliverable" refid="_16_6_27c0135_1323963711132_828711_12886"/><operation humanType="Operation" icon="UX_files/icon_25941162.png" name="uploadArtifact" refid="_16_6_27c0135_1323963764639_574514_12888"/></member><name humanName="Name" mode="expert">Deliverables List</name><namespace humanName="Namespace" humanType="Package" icon="UX_files/icon_21279106.png" name="Student" refid="_16_8_2030113_1324131980640_668457_18100"/><ownedAttribute humanName="Owned Attribute"><property humanType="Property" icon="UX_files/icon_18207639.png" name="" refid="_16_6_27c0135_1323963805355_429964_12898"/><property humanType="Property" icon="UX_files/icon_18207639.png" name="" refid="_16_6_27c0135_1323964526145_780649_12996"/><property humanType="Property" icon="UX_files/icon_18207639.png" name="" refid="_16_5_4_2030113_1323967839093_586719_406"/><property humanType="Property" icon="UX_files/icon_18207639.png" name="" refid="_16_5_4_2030113_1323973054390_652871_2236"/><property humanType="Property" icon="UX_files/icon_18207639.png" name="" refid="_16_5_4_2030113_1323986344703_930940_1752"/><property humanType="Property" icon="UX_files/icon_18207639.png" name="" refid="_16_5_4_2030113_1323988334593_68790_2532"/><property humanType="Property" icon="UX_files/icon_18207639.png" name="deliverable" refid="_16_6_27c0135_1323963711132_828711_12886"/></ownedAttribute><ownedElement humanName="Owned Element"><instancespecification humanType="Instance Specification" icon="UX_files/icon_22306013.png" name="" refid="_16_6_27c0135_1323963703188_246104_12885"/><property humanType="Property" icon="UX_files/icon_18207639.png" name="" refid="_16_6_27c0135_1323963805355_429964_12898"/><property humanType="Property" icon="UX_files/icon_18207639.png" name="" refid="_16_6_27c0135_1323964526145_780649_12996"/><property humanType="Property" icon="UX_files/icon_18207639.png" name="" refid="_16_5_4_2030113_1323967839093_586719_406"/><property humanType="Property" icon="UX_files/icon_18207639.png" name="" refid="_16_5_4_2030113_1323973054390_652871_2236"/><property humanType="Property" icon="UX_files/icon_18207639.png" name="" refid="_16_5_4_2030113_1323986344703_930940_1752"/><property humanType="Property" icon="UX_files/icon_18207639.png" name="" refid="_16_5_4_2030113_1323988334593_68790_2532"/><property humanType="Property" icon="UX_files/icon_18207639.png" name="deliverable" refid="_16_6_27c0135_1323963711132_828711_12886"/><operation humanType="Operation" icon="UX_files/icon_25941162.png" name="uploadArtifact" refid="_16_6_27c0135_1323963764639_574514_12888"/></ownedElement><ownedMember humanName="Owned Member"><property humanType="Property" icon="UX_files/icon_18207639.png" name="" refid="_16_6_27c0135_1323963805355_429964_12898"/><property humanType="Property" icon="UX_files/icon_18207639.png" name="" refid="_16_6_27c0135_1323964526145_780649_12996"/><property humanType="Property" icon="UX_files/icon_18207639.png" name="" refid="_16_5_4_2030113_1323967839093_586719_406"/><property humanType="Property" icon="UX_files/icon_18207639.png" name="" refid="_16_5_4_2030113_1323973054390_652871_2236"/><property humanType="Property" icon="UX_files/icon_18207639.png" name="" refid="_16_5_4_2030113_1323986344703_930940_1752"/><property humanType="Property" icon="UX_files/icon_18207639.png" name="" refid="_16_5_4_2030113_1323988334593_68790_2532"/><property humanType="Property" icon="UX_files/icon_18207639.png" name="deliverable" refid="_16_6_27c0135_1323963711132_828711_12886"/><operation humanType="Operation" icon="UX_files/icon_25941162.png" name="uploadArtifact" refid="_16_6_27c0135_1323963764639_574514_12888"/></ownedMember><ownedOperation humanName="Owned Operation"><operation humanType="Operation" icon="UX_files/icon_25941162.png" name="uploadArtifact" refid="_16_6_27c0135_1323963764639_574514_12888"/></ownedOperation><owner humanName="Owner" humanType="Package" icon="UX_files/icon_21279106.png" name="Student" refid="_16_8_2030113_1324131980640_668457_18100"/><owningPackage humanName="Owning Package" humanType="Package" icon="UX_files/icon_21279106.png" name="Student" refid="_16_8_2030113_1324131980640_668457_18100"/><package humanName="Package" humanType="Package" icon="UX_files/icon_21279106.png" name="Student" refid="_16_8_2030113_1324131980640_668457_18100"/><part humanName="Part"><property humanType="Property" icon="UX_files/icon_18207639.png" name="" refid="_16_6_27c0135_1323964526145_780649_12996"/></part><qualifiedName humanName="Qualified Name">Resources::Student::Deliverables List</qualifiedName><visibility humanName="Visibility">public</visibility></class></magicdraw>