<?xml version="1.0" encoding="UTF-8"?>
<magicdraw><componentrealization humanType="Component Realization" icon="UX_files/icon_30814417.png" id="_16_6_27c0135_1324025136044_92475_13471"><abstraction humanName="Abstraction" humanType="GroupBox" icon="UX_files/icon_33223425.png" mode="standard,expert" name="" refid="_16_6_27c0135_1324025014907_193933_13184"/><client humanName="Client"><button humanType="Button" icon="UX_files/icon_15370511.png" name="" refid="_16_6_27c0135_1324025136034_70578_13465"/></client><name humanName="Name" mode="standard,expert"/><owner humanName="Owner" humanType="GroupBox" icon="UX_files/icon_33223425.png" mode="standard,expert" name="" refid="_16_6_27c0135_1324025014907_193933_13184"/><qualifiedName humanName="Qualified Name" mode="expert">Resources::Student::::</qualifiedName><realizingClassifier humanName="Realizing Classifier" mode="standard,expert"><button humanType="Button" icon="UX_files/icon_15370511.png" name="" refid="_16_6_27c0135_1324025136034_70578_13465"/></realizingClassifier><relatedElement humanName="Related Element"><button humanType="Button" icon="UX_files/icon_15370511.png" name="" refid="_16_6_27c0135_1324025136034_70578_13465"/><groupbox humanType="GroupBox" icon="UX_files/icon_33223425.png" name="" refid="_16_6_27c0135_1324025014907_193933_13184"/></relatedElement><source humanName="Source"><button humanType="Button" icon="UX_files/icon_15370511.png" name="" refid="_16_6_27c0135_1324025136034_70578_13465"/></source><supplier humanName="Supplier"><groupbox humanType="GroupBox" icon="UX_files/icon_33223425.png" name="" refid="_16_6_27c0135_1324025014907_193933_13184"/></supplier><target humanName="Target"><groupbox humanType="GroupBox" icon="UX_files/icon_33223425.png" name="" refid="_16_6_27c0135_1324025014907_193933_13184"/></target><visibility humanName="Visibility">public</visibility></componentrealization></magicdraw>